<?xml version="1.0" encoding="utf-8"?>
<search>
  
  
  
  <entry>
    <title>小肥阳的小学生日记1</title>
    <link href="/aLifelongLove/2021/05/02/2021-05-01-%E5%B0%8F%E8%82%A5%E9%98%B3%E6%97%A5%E8%AE%B01/"/>
    <url>/aLifelongLove/2021/05/02/2021-05-01-%E5%B0%8F%E8%82%A5%E9%98%B3%E6%97%A5%E8%AE%B01/</url>
    
    <content type="html"><![CDATA[<h1 id="小肥阳日记第一则"><a href="#小肥阳日记第一则" class="headerlink" title="小肥阳日记第一则"></a>小肥阳日记第一则</h1><p>今天是5月2日，小肥阳睡得很晚才起来去图书馆，和娴娴一起出门，小肥阳买了两个烧麦吃了，娴娴推荐的，有点好吃。<br>今天的长沙很热，小肥阳起来就发现了，但小肥阳忘记晒被子了，要是和麻麻说又要被麻麻说道了。<br>小肥阳约了十点半的图书馆，十点钟就到了，坐下来准备刷六级，做了几套听力之后小肥阳发现六级听力也不是很难，就算听不懂，能听到关键词就行，但是小肥阳总是抓不住关键词，每次都拿不到60%的听力分，小肥阳很难过。一定是不够专心，一听听力就容易睡着，小肥阳想。要是能一直很专注就好了。<br>小肥阳背了作文，好久没记单词了，小肥阳有点懊恼，今天看了一篇翻译，发现里面的句子名词很多都不会写，小肥阳很难过。<br>到了中午兴伟来了，嘿嘿，和男朋友一起自习的感觉真好。<br>小肥阳今天找到了背书的那个小空间，是一个漂亮小姐姐带小肥阳去的，小姐姐人美心善！<br>今天小肥阳的学习很慢吞吞，学习效率不高，小肥阳的听力还要继续加油喔。<br>和男朋友一起吃到了蜜雪冰城的冰淇淋是小肥阳今天最快乐的事情了，天知道小肥阳想吃这个冰淇淋想了多久了！</p><p><img src="https://img-blog.csdnimg.cn/20210502203234232.jpeg?x-oss-process=image/watermark,type_ZmFuZ3poZW5naGVpdGk,shadow_10,text_aHR0cHM6Ly9ibG9nLmNzZG4ubmV0L20wXzU3ODQyNjg2,size_16,color_FFFFFF,t_70#pic_center" alt="小肥阳爱吃的冰淇淋"></p><p>这是小肥阳第一次这样写日记，小肥阳也不知道格式对不对，这个图片好像可以<del>直接添加</del>，小肥阳不确定，因为兴伟教的是用==链接==，可是小肥阳<em>不会</em>。</p><p>感觉好像还可以，<strong>小肥阳真聪明</strong>！</p><p>今天的日记就到这里吧。</p><p>举一反三，**==小肥阳会加粗+添加背景色==**小肥阳真聪明欸！</p><p>**==小肥阳好喜欢她男朋友欸==**！</p>]]></content>
    
    
    <categories>
      
      <category>日记</category>
      
      <category>小肥阳撰写</category>
      
    </categories>
    
    
    <tags>
      
      <tag>烧麦</tag>
      
      <tag>热</tag>
      
      <tag>图书馆</tag>
      
      <tag>六级听力</tag>
      
      <tag>自习</tag>
      
      <tag>男朋友</tag>
      
      <tag>蜜雪冰城</tag>
      
      <tag>聪明</tag>
      
    </tags>
    
  </entry>
  
  
  
  <entry>
    <title>王亡於江上</title>
    <link href="/aLifelongLove/2020/12/15/2020-12-15-%E3%80%8A%E7%8E%8B%E4%BA%A1%E6%96%BC%E6%B1%9F%E4%B8%8A%E3%80%8B/"/>
    <url>/aLifelongLove/2020/12/15/2020-12-15-%E3%80%8A%E7%8E%8B%E4%BA%A1%E6%96%BC%E6%B1%9F%E4%B8%8A%E3%80%8B/</url>
    
    <content type="html"><![CDATA[<h1 id="王亡於江上"><a href="#王亡於江上" class="headerlink" title="王亡於江上"></a>王亡於江上</h1><blockquote><p>昭王之时，王道微缺。<br>昭王南巡狩不返，卒於江上。<br>其卒不赴告，讳之也。<br>–《史记》</p></blockquote><h2 id="故事概要"><a href="#故事概要" class="headerlink" title="故事概要"></a>故事概要</h2><p><em>昭王十七年，伐楚国，莘公立功，不讨封赏。</em><br><em>昭王十八年春，楚新君熊黵即位，入朝献地联姻。昭王私见楚女，甚是喜欢，赐胙肉，加封楚君。熊黵以行楚礼为由，请带楚女先行归国；因担心昭王留恋私情，莘公领群臣力谏昭王。昭王允之，亲自送行。</em><br><em>昭王十八年九月初吉，昭王布告诸侯，将南巡淮河下游，莘公、蔡叔等同往。同时，楚女芈婉向其兄熊黵请往北方以采雪莲，与昭王私会淮河上游。巴国质楚公子，盗取其表兄熊黵兵符，领重兵包围昭王。芈婉回楚营退兵，昭王回营整队，不想回营途中，船只为楚人变更，淹死江中，莘由靡打捞尸体秘不发丧，回周后拥太子满即位。</em></p><h2 id="详细故事"><a href="#详细故事" class="headerlink" title="详细故事"></a>详细故事</h2><p><code>武王伐纣，武王十五年，成王即位，成王二十又一年传康王，康王在位二十五年，三代政绩卓著，诸侯归心，礼乐严明，周室兴盛，史称“成康之治”，康王崩，昭王即位，昭王行事古怪，好战，多次征伐南方，不受平民和边境诸侯爱戴，自此王道始缺。</code></p><p><code>昭王十六年，率诸侯伐楚国，楚国大败，楚君熊艾战后病故，其子熊黵继承其子爵，领楚国，为楚国第三代国君。 昭王十七年，春，熊黵前往畿进贡请胙，携带金玉、奴隶、侍女献给昭王，同行的还有其妹妹芈婉，芈婉国色天香，美丽动人，熊黵欲求姻于天子，来讨回去年战败失地。</code></p><p><code>昭王这边准备将去年赢得的楚地赏赐给常伴自己左右的莘国国君莘由靡，故迟迟不接见熊黵。莘由靡劝谏昭王接见熊黵，昭王便让熊黵晚上进殿朝贡。熊黵提前用银钱买通宫中寺人，安排了芈婉和昭王偶遇，昭王对芈婉一见倾心，欲封芈婉为后，并将失地还与楚国。在朝堂之上力压百官，要求封芈婉为后，熊黵见周室朝堂如此反对，担心客死周王畿，请求先带芈婉回楚国准备嫁娶连日赶回楚国。</code></p><p><code>熊黵回楚后，巴国质楚公子和熊黵密谋设计欲杀昭王。 而芈婉，也对昭王恋恋不忘，竟然在离开周王畿时约定让昭王九月初吉到楚国境内淮水源头相会。而巴涂暗恋芈婉，在约芈婉外出游玩中无意发现此事，立即告诉熊黵。</code></p><p><code>熊黵和巴涂两人想借此机会将昭王杀死，以报周室多年欺压之仇。 八月，昭王果然布告诸侯，南巡狩猎。蔡叔随行，莘由靡为昭王驾车，一路狩猎至楚国边境。</code></p><p><code>芈婉与此同时也谎称采摘千年水莲前往淮水源头，私会昭王。熊黵却派巴涂领兵尾随。 昭王命蔡叔驻军在淮水北面，自己与莘由靡驾小船到淮水南面接应芈婉。</code></p><p><code>见到芈婉后却被楚兵追杀，芈婉留下前去劝退楚兵，昭王和莘由靡原路返回。到江边后发现蔡叔也渡江过来，但三人回江边后，船都被损毁了。昭王蔡叔沿江往东寻找船只，莘由靡沿江往西寻找船只。</code></p><p><code>芈婉这边在与巴涂纠缠，而后巴涂和芈婉讲明事情原委，芈婉知道真相后跳入江中，被巴涂救起带回楚国。原来熊黵不想担负弑君的罪名，害怕被周室征讨，便派二三农夫到淮水边上损坏船只，并在江边放置许多胶船。</code></p><p><code>昭王这边却急于渡江，乘坐胶船淹死在江中。莘由靡水性好，游回了淮水北侧，在江边打捞起昭王和蔡叔的尸体。莘由靡害怕消息传回周王畿会有人作乱，于是密不发丧。</code></p><p><code>昭王十九年，太子满即位，是为穆王，诰命天下诸侯朝贡。</code></p><p><code>芈婉听闻周王畿传来新王即位的诰书，半月不食而亡。</code></p><h2 id="人物概要"><a href="#人物概要" class="headerlink" title="人物概要"></a>人物概要</h2><p><em>人物故事可详见《王亡於江上》之周昭王姬瑕、《王亡於江上》之楚国君熊黵、《王亡於江上》之莘由靡、《王亡於江上》之芈婉，故事更多，情节更丰富哦！</em></p><p><code>昭王：姬瑕，周室第四代天子，多次南征，称南方诸国为蛮夷；喜欢芈婉，南巡私会芈婉，情急之下淹死淮水之中。</code></p><p><code>熊黵：楚国第三代君主，痛恨天子对楚国有偏见。芈婉的亲哥哥，用芈婉诱惑昭王，并设计成功害死了昭王。</code></p><p><code>莘由靡：周王畿旁边的莘国国君，常年侍奉昭王，同昭王一起在宫中长大，在昭王征伐楚国时，立下功劳。陪昭王一起南巡，昭王溺死后，密不发丧，带昭王尸体回周王畿后，拥太子满即位。</code></p><p><code>芈婉：熊黵妹妹，随兄长一起进贡朝拜昭王，在熊黵的促使下，与昭王相见，并与昭王一见倾心。与昭王约定在昭王十九年九月相会淮水，却不小心被巴涂偷偷知晓并报告给了熊黵。九月前往私会昭王，知道哥哥的阴谋后，跳江未遂。回楚国后，绝食而亡。</code></p><p>==本文及其附属文章故事均为虚构，切莫当作真实历史故事。昭王在历史上确有此人，但《史记》仅仅只用一句话描述了这位溺水君王的一生。==</p>]]></content>
    
    
    <categories>
      
      <category>周时故事</category>
      
      <category>兴伟撰写</category>
      
    </categories>
    
    
    <tags>
      
      <tag>历史</tag>
      
      <tag>周昭王</tag>
      
    </tags>
    
  </entry>
  
  
  
  <entry>
    <title>撰写文章规范</title>
    <link href="/aLifelongLove/2020/02/02/hello-world/"/>
    <url>/aLifelongLove/2020/02/02/hello-world/</url>
    
    <content type="html"><![CDATA[<p>我的小宝贝，这是为你写的一个整理文章的平台，下面由我这篇文章来告诉你怎么撰写文章的规范吧。</p><h2 id="文章规范"><a href="#文章规范" class="headerlink" title="文章规范"></a>文章规范</h2><h3 id="markdown文本语法"><a href="#markdown文本语法" class="headerlink" title="markdown文本语法"></a>markdown文本语法</h3><p>这个语法最常用于写博客文章，里面很适合融入代码，<br>但是它不单单可以写博客，它可以用来写记录生活的文章，<br>可以抒发感情，可以插入图片，可以插入视频，<br>可以像编辑一个公众号文章一样随心所欲，<br>不过初次写这样的文章，可能会碰很多坑。<br>我们可以进入<a href="https://www.csdn.net/">CSDN</a> 然后在它的在线编辑工具里学习这中文法。</p><p><img src="https://img-blog.csdnimg.cn/20210430200204915.png?x-oss-process=image/watermark,type_ZmFuZ3poZW5naGVpdGk,shadow_10,text_aHR0cHM6Ly9ibG9nLmNzZG4ubmV0L3FxXzQzMjg5NzEx,size_16,color_FFFFFF,t_70" alt="CSDN编辑工具截图"></p><h3 id="将写好的marhdown-md-文档上传到此站点"><a href="#将写好的marhdown-md-文档上传到此站点" class="headerlink" title="将写好的marhdown(.md)文档上传到此站点"></a>将写好的marhdown(.md)文档上传到此站点</h3><p>由于上传文章需要配置hexo环境和github仓库，这些我在自己电脑上做了，要是帮你配置好，你可能也也不会用。<br>所以要上传任何东西，我可以代理奥。<br>但是你要按照markdown语法规范来奥，不然文章的样式不能保证。<br>（如果有样式和图片的话，尽量先到CSDN的编辑器里写好）</p><h3 id="文章的属性"><a href="#文章的属性" class="headerlink" title="文章的属性"></a>文章的属性</h3><p>每篇文章都可以有属性奥，这些属性都是可以自定义的。<br>一般有以下属性：标题，时间，作者，分类，标签<br>这些属性要写在文章的开头：<br><img src="https://img-blog.csdnimg.cn/20210430201558479.png?x-oss-process=image/watermark,type_ZmFuZ3poZW5naGVpdGk,shadow_10,text_aHR0cHM6Ly9ibG9nLmNzZG4ubmV0L3FxXzQzMjg5NzEx,size_16,color_FFFFFF,t_70" alt="md文档的文章属性"><br>正如上面图片所示，我写的这个规范文章的属性，就在开头的—和—之间</p><figure class="highlight c"><table><tr><td class="gutter"><pre><span class="line">1</span><br><span class="line">2</span><br><span class="line">3</span><br><span class="line">4</span><br><span class="line">5</span><br><span class="line">6</span><br><span class="line">7</span><br><span class="line">8</span><br><span class="line">9</span><br><span class="line">10</span><br><span class="line">11</span><br></pre></td><td class="code"><pre><code class="hljs c">---<br>title: 撰写文章规范<br>date: <span class="hljs-number">2020</span>/<span class="hljs-number">2</span>/<span class="hljs-number">2</span> <span class="hljs-number">12</span>:<span class="hljs-number">00</span>:<span class="hljs-number">00</span><br>author: 兴伟<br>categories:<br>    - 规范<br>tags:<br>    - HEXO<br>    - 教程<br>    - 兴伟撰写<br>---<br></code></pre></td></tr></table></figure>]]></content>
    
    
    <categories>
      
      <category>兴伟撰写</category>
      
      <category>教程</category>
      
    </categories>
    
    
    <tags>
      
      <tag>HEXO</tag>
      
    </tags>
    
  </entry>
  
  
  
  <entry>
    <title>如何写规范的文档</title>
    <link href="/aLifelongLove/2020/02/02/markdown%E8%AF%AD%E6%B3%95/"/>
    <url>/aLifelongLove/2020/02/02/markdown%E8%AF%AD%E6%B3%95/</url>
    
    <content type="html"><![CDATA[<h1 id="基本概念"><a href="#基本概念" class="headerlink" title="基本概念"></a>基本概念</h1><ul><li>换行是不要钱的，只要不是连续的文本都可以在中间加一个或多个换行，无论输入多少空行，最终显示的效果也是没有空行的。</li><li>本质都是文字，只是会使用一些符号来放在这一行文本的开头，来设置这一行文本的格式。</li><li>注意标记符号和文本内容要有一个距离，一般是一个空格或一个换行。</li><li>所有的图片都是根据链接地址寻找的，所以这张图片要先上传到网络，并得到他的链接。</li></ul><h1 id="先写标题"><a href="#先写标题" class="headerlink" title="先写标题"></a>先写标题</h1><p>标题有等级，等级随<code>#</code>的个数增加而降低，最高级的一个<code>#</code>，比如我的文档写的内容如下：<br>(注意<code>#</code>和标题文本之间要留一个空格)</p><figure class="highlight vala"><table><tr><td class="gutter"><pre><span class="line">1</span><br><span class="line">2</span><br><span class="line">3</span><br><span class="line">4</span><br><span class="line">5</span><br></pre></td><td class="code"><pre><code class="hljs vala"><span class="hljs-meta"># 一级标题1</span><br><span class="hljs-meta">## 二级标题1</span><br><span class="hljs-meta">### 三级标题1</span><br><span class="hljs-meta">## 二级标题2</span><br><span class="hljs-meta"># 一级标题2</span><br></code></pre></td></tr></table></figure><p>那么它显示的效果如下：</p><blockquote><h1 id="一级标题1"><a href="#一级标题1" class="headerlink" title="一级标题1"></a>一级标题1</h1><h2 id="二级标题1"><a href="#二级标题1" class="headerlink" title="二级标题1"></a>二级标题1</h2><h3 id="三级标题1"><a href="#三级标题1" class="headerlink" title="三级标题1"></a>三级标题1</h3><h2 id="二级标题2"><a href="#二级标题2" class="headerlink" title="二级标题2"></a>二级标题2</h2><h1 id="一级标题2"><a href="#一级标题2" class="headerlink" title="一级标题2"></a>一级标题2</h1></blockquote><p>我们应该在文章里比较均匀合理的设置小标题，方便理清文章的层次结构。</p><h1 id="写普通文本"><a href="#写普通文本" class="headerlink" title="写普通文本"></a>写普通文本</h1><p>普通文本还是占文章的大部分，也就是没有用任何特殊符号来标记修饰的文本。</p><h1 id="文本样式"><a href="#文本样式" class="headerlink" title="文本样式"></a>文本样式</h1><p>在众多的普通文本中，总有些文本是我们希望他们不一样，比如：</p><figure class="highlight asciidoc"><table><tr><td class="gutter"><pre><span class="line">1</span><br><span class="line">2</span><br><span class="line">3</span><br><span class="line">4</span><br></pre></td><td class="code"><pre><code class="hljs asciidoc">普通样式：电话号码119是火警电话<br>行内代码：电话号码<span class="hljs-code">``119``</span>是火警电话<br>强调样式：电话号码<span class="hljs-strong">*119*</span>是火警电话<br>加粗样式：电话号码<span class="hljs-strong">**119**</span>是火警电话<br></code></pre></td></tr></table></figure><p>它们对应的效果：</p><blockquote><p>普通样式：电话号码119是火警电话<br>行内代码：电话号码<code>119</code>是火警电话<br>强调样式：电话号码<em>119</em>是火警电话<br>加粗样式：电话号码<strong>119</strong>是火警电话</p></blockquote><h1 id="段落样式"><a href="#段落样式" class="headerlink" title="段落样式"></a>段落样式</h1><p>一般常用的有引用格式和代码片段</p><blockquote><p>这里是引用格式<br>看起来很清爽<br>仿佛置身局外一样<br>这是在每一行的开头添加一个<code>&gt;</code>符号得到的</p></blockquote><figure class="highlight autohotkey"><table><tr><td class="gutter"><pre><span class="line">1</span><br><span class="line">2</span><br><span class="line">3</span><br><span class="line">4</span><br></pre></td><td class="code"><pre><code class="hljs autohotkey">这里是代码片格式<br>看起来很专业<br>是专门放代码片段的地方<br>这是在段落的开头和结尾都用```来标记<br></code></pre></td></tr></table></figure><h1 id="图片"><a href="#图片" class="headerlink" title="图片"></a>图片</h1><p>图片都是根据链接来得到的，便于移植。</p><h2 id="固定大小形式："><a href="#固定大小形式：" class="headerlink" title="固定大小形式："></a>固定大小形式：</h2><figure class="highlight less"><table><tr><td class="gutter"><pre><span class="line">1</span><br><span class="line">2</span><br></pre></td><td class="code"><pre><code class="hljs less">!<span class="hljs-selector-attr">[图片描述信息]</span>(link)<br>!<span class="hljs-selector-attr">[CSDN编辑工具]</span>(<span class="hljs-attribute">https</span>:<span class="hljs-comment">//img-blog.csdnimg.cn/20210501015405692.png?x-oss-process=image/watermark,type_ZmFuZ3poZW5naGVpdGk,shadow_10,text_aHR0cHM6Ly9ibG9nLmNzZG4ubmV0L3FxXzQzMjg5NzEx,size_16,color_FFFFFF,t_70)</span><br></code></pre></td></tr></table></figure><p>下面这张图就是上面第二行的图片效果：</p><p><img src="https://img-blog.csdnimg.cn/20210501015405692.png?x-oss-process=image/watermark,type_ZmFuZ3poZW5naGVpdGk,shadow_10,text_aHR0cHM6Ly9ibG9nLmNzZG4ubmV0L3FxXzQzMjg5NzEx,size_16,color_FFFFFF,t_70" alt="CSDN编辑工具"></p><h2 id="可变大小形式"><a href="#可变大小形式" class="headerlink" title="可变大小形式"></a>可变大小形式</h2><figure class="highlight routeros"><table><tr><td class="gutter"><pre><span class="line">1</span><br><span class="line">2</span><br></pre></td><td class="code"><pre><code class="hljs routeros">&lt;img <span class="hljs-attribute">width</span>=<span class="hljs-string">&quot;mpx;&quot;</span> <span class="hljs-attribute">height</span>=<span class="hljs-string">&quot;npx;&quot;</span> <span class="hljs-attribute">alt</span>=<span class="hljs-string">&quot;message&quot;</span> <span class="hljs-attribute">src</span>=<span class="hljs-string">&quot;link&quot;</span>/&gt;<br>&lt;img <span class="hljs-attribute">width</span>=<span class="hljs-string">&quot;500px;&quot;</span> <span class="hljs-attribute">height</span>=<span class="hljs-string">&quot;250px;&quot;</span> <span class="hljs-attribute">alt</span>=<span class="hljs-string">&quot;CSDN编辑工具&quot;</span> <span class="hljs-attribute">src</span>=<span class="hljs-string">&quot;https://img-blog.csdnimg.cn/20210501015405692.png?x-oss-process=image/watermark,type_ZmFuZ3poZW5naGVpdGk,shadow_10,text_aHR0cHM6Ly9ibG9nLmNzZG4ubmV0L3FxXzQzMjg5NzEx,size_16,color_FFFFFF,t_70&quot;</span>/&gt;<br></code></pre></td></tr></table></figure><p>在第一行中，<code>m</code> <code>n</code> <code>message</code> <code>link</code>依次是宽，高，图片信息，图片链接<br>第二行是一个示例，它的效果如下：<br><img width="500px;" height="250px;" alt="CSDN编辑工具" src="https://img-blog.csdnimg.cn/20210501015405692.png?x-oss-process=image/watermark,type_ZmFuZ3poZW5naGVpdGk,shadow_10,text_aHR0cHM6Ly9ibG9nLmNzZG4ubmV0L3FxXzQzMjg5NzEx,size_16,color_FFFFFF,t_70"/></p><h1 id="其他一些结构"><a href="#其他一些结构" class="headerlink" title="其他一些结构"></a>其他一些结构</h1><h2 id="列表"><a href="#列表" class="headerlink" title="列表"></a>列表</h2><figure class="highlight markdown"><table><tr><td class="gutter"><pre><span class="line">1</span><br><span class="line">2</span><br><span class="line">3</span><br><span class="line">4</span><br><span class="line">5</span><br><span class="line">6</span><br><span class="line">7</span><br></pre></td><td class="code"><pre><code class="hljs markdown"><span class="hljs-bullet">+</span> 第一行<br><span class="hljs-bullet">+</span> 第二行<br><span class="hljs-bullet">+</span> 第三行<br><br><span class="hljs-bullet">1.</span> 第一行<br><span class="hljs-bullet">2.</span> 第二行<br><span class="hljs-bullet">3.</span> 第三行<br></code></pre></td></tr></table></figure><p>注意<code>+</code>以及<code>1.</code> <code>2.</code> <code>3.</code>与它们后面的文本有一个空格<br>他们的演示效果为：</p><ul><li>第一行</li><li>第二行</li><li>第三行</li></ul><ol><li>第一行</li><li>第二行</li><li>第三行</li></ol><h1 id="最后"><a href="#最后" class="headerlink" title="最后"></a>最后</h1><p>掌握以上基础，写一个简洁大方的markdown文档已经不成问题，另外平时需要其他更多样式的时候要大胆的百度搜索，因为上面仅仅只是一小部分。而且markdown是兼容html的，所以样式很多很多。</p><h1 id="额外一点"><a href="#额外一点" class="headerlink" title="额外一点"></a>额外一点</h1><p>针对我们自己上传的markdown文档，会在开头加上这篇文章的属性，便于对文章管理，它们犹如文章的身份证，格式如下：</p><figure class="highlight yaml"><table><tr><td class="gutter"><pre><span class="line">1</span><br><span class="line">2</span><br><span class="line">3</span><br><span class="line">4</span><br><span class="line">5</span><br><span class="line">6</span><br><span class="line">7</span><br><span class="line">8</span><br><span class="line">9</span><br><span class="line">10</span><br><span class="line">11</span><br><span class="line">12</span><br><span class="line">13</span><br></pre></td><td class="code"><pre><code class="hljs yaml"><span class="hljs-meta">---</span><br><br><span class="hljs-attr">title:</span> <span class="hljs-string">如何写规范的文档</span><br><span class="hljs-attr">date:</span> <span class="hljs-number">2020</span><span class="hljs-string">/2/2</span> <span class="hljs-number">12</span><span class="hljs-string">:00:00</span><br><span class="hljs-attr">author:</span> <span class="hljs-string">兴伟</span><br><span class="hljs-attr">categories:</span><br>    <span class="hljs-bullet">-</span> <span class="hljs-string">规范</span><br><span class="hljs-attr">tags:</span><br>    <span class="hljs-bullet">-</span> <span class="hljs-string">markdown</span><br>    <span class="hljs-bullet">-</span> <span class="hljs-string">教程</span><br>    <span class="hljs-bullet">-</span> <span class="hljs-string">兴伟撰写</span><br><br><span class="hljs-meta">---</span><br></code></pre></td></tr></table></figure><p>其中：</p><ul><li><code>title</code>是标题，写这个文章的标题</li><li><code>date</code>是时间，按格式写时间</li><li><code>author</code>是作者，随便写</li><li><code>categories</code>是分类名，随便写，自己想给它分到什么类就什么类，可以分多个类，但建议只指定一个类</li><li><code>tags</code>是标签，随便写，与分类作用类似，但是更偏向内容，一般是几个重要的关键字。</li></ul><p>注意：<code>:</code>和<code>-</code>与文本之间存在一个空格，不是直接相连，并且<code>-</code>距离行首是一个<code>tab</code>键的距离。</p>]]></content>
    
    
    <categories>
      
      <category>兴伟撰写</category>
      
      <category>教程</category>
      
    </categories>
    
    
    <tags>
      
      <tag>markdown</tag>
      
      <tag>文法</tag>
      
    </tags>
    
  </entry>
  
  
  
  
</search>
